LICENSE.txt
README.md
setup.py
yassine_ramla_rocket/__init__.py
yassine_ramla_rocket/yassine_ramla_rocket.py
yassine_ramla_rocket.egg-info/PKG-INFO
yassine_ramla_rocket.egg-info/SOURCES.txt
yassine_ramla_rocket.egg-info/dependency_links.txt
yassine_ramla_rocket.egg-info/top_level.txt