Metadata-Version: 2.1
Name: yassine_ramla_rocket
Version: 1.0.1
Summary: An awesome package to create some rockets
Home-page: http://pypi.python.org/pypi/yassine_ramla_rocket/
Author: yassine ramla
Author-email: y.ramla@esi-sba.dz
License: LICENSE.txt
License-File: LICENSE.txt
